tankersdk_identity/__init__.py
tankersdk_identity/crypto/__init__.py
tankersdk_identity/py.typed
tankersdk_identity/test/__init__.py
tankersdk_identity/test/conftest.py
tankersdk_identity/test/helpers.py
tankersdk_identity/test/test_crypto.py
tankersdk_identity/test/test_identity.py
tankersdk_identity/test/test_vectors.py
tankersdk_identity-3.3.3.dist-info/LICENSE
tankersdk_identity-3.3.3.dist-info/METADATA
tankersdk_identity-3.3.3.dist-info/WHEEL
tankersdk_identity-3.3.3.dist-info/RECORD
