Metadata-Version: 2.1
Name: tankersdk-identity
Version: 3.3.3
Summary: Tanker identity library
Home-page: https://github.com/TankerHQ/identity-python
Author: Tanker team
Requires-Python: >=3.9,<4
Classifier: Programming Language :: Python :: 3
Classifier: Programming Language :: Python :: 3.9
Classifier: Programming Language :: Python :: 3.10
Classifier: Programming Language :: Python :: 3.11
Classifier: Programming Language :: Python :: 3.12
Requires-Dist: PyNacl (==1.5.0)
